{
    "boxShadow": "none",
    "widgetName": "key_scale_container",
    "isFilterable": true,
    "dynamicPropertyPathList": [{"key": "onOptionChange"}],
    "iconSVG": "/static/media/icon.bd99caba5853ad71e4b3d8daffacb3a2.svg",
    "displayName": "Select",
    "labelText": "Select Key",
    "topRow": 62.0000000000087,
    "searchTags": ["dropdown"],
    "bottomRow": 69.00000000000509,
    "parentRowSpace": 10,
    "labelWidth": 5,
    "type": "SELECT_WIDGET",
    "serverSideFiltering": false,
    "hideCard": false,
    "defaultOptionValue": "GREEN",
    "animateLoading": true,
    "parentColumnSpace": 5.67578125,
    "dynamicTriggerPathList": [{"key": "onOptionChange"}],
    "leftColumn": 0,
    "dynamicBindingPathList": [
        {"key": "accentColor"},
        {"key": "borderRadius"},
        {"key": "sourceData"}
    ],
    "labelPosition": "Top",
    "placeholderText": "Select option",
    "isDisabled": false,
    "sourceData": "{{get_song_keys.data}}",
    "key": "x6zzlwmi55",
    "labelTextSize": "0.875rem",
    "isRequired": false,
    "isDeprecated": false,
    "rightColumn": 63,
    "dynamicHeight": "FIXED",
    "accentColor": "{{appsmith.theme.colors.primaryColor}}",
    "widgetId": "7hilxkkhyk",
    "optionValue": "value",
    "minWidth": 450,
    "isVisible": true,
    "version": 1,
    "parentId": "pjvxmre18g",
    "isLoading": false,
    "labelAlignment": "left",
    "renderMode": "CANVAS",
    "optionLabel": "label",
    "originalTopRow": 62.0000000000058,
    "borderRadius": "{{appsmith.theme.borderRadius.appBorderRadius}}",
    "maxDynamicHeight": 9000,
    "originalBottomRow": 69.00000000000364,
    "onOptionChange": "{{appsmith.store.key = key_scale_container.selectedOptionValue}}",
    "minDynamicHeight": 4
}